gaussianprocessderivatives/CLAUDE.md
gaussianprocessderivatives/__init__.py
gaussianprocessderivatives/gaussianprocess.py
gaussianprocessderivatives/linGP.py
gaussianprocessderivatives/localperiodicGP.py
gaussianprocessderivatives/maternGP.py
gaussianprocessderivatives/nnGP.py
gaussianprocessderivatives/periodicGP.py
gaussianprocessderivatives/spectralmixingGP.py
gaussianprocessderivatives/sqexpGP.py
gaussianprocessderivatives/sqexplinGP.py
gaussianprocessderivatives-0.1.68.dist-info/METADATA
gaussianprocessderivatives-0.1.68.dist-info/WHEEL
gaussianprocessderivatives-0.1.68.dist-info/RECORD
